CustomAuth/.gitignore
CustomAuth/LICENSE
CustomAuth/README.md
CustomAuth/__init__.py
CustomAuth/apps.py
CustomAuth/tests.py
CustomAuth/.git/COMMIT_EDITMSG
CustomAuth/.git/HEAD
CustomAuth/.git/ORIG_HEAD
CustomAuth/.git/config
CustomAuth/.git/description
CustomAuth/.git/index
CustomAuth/.git/hooks/applypatch-msg.sample
CustomAuth/.git/hooks/commit-msg.sample
CustomAuth/.git/hooks/fsmonitor-watchman.sample
CustomAuth/.git/hooks/post-update.sample
CustomAuth/.git/hooks/pre-applypatch.sample
CustomAuth/.git/hooks/pre-commit.sample
CustomAuth/.git/hooks/pre-push.sample
CustomAuth/.git/hooks/pre-rebase.sample
CustomAuth/.git/hooks/pre-receive.sample
CustomAuth/.git/hooks/prepare-commit-msg.sample
CustomAuth/.git/hooks/update.sample
CustomAuth/.git/info/exclude
CustomAuth/.git/logs/HEAD
CustomAuth/.git/logs/refs/stash
CustomAuth/.git/logs/refs/heads/develop
CustomAuth/.git/logs/refs/heads/master
CustomAuth/.git/logs/refs/remotes/github/master
CustomAuth/.git/logs/refs/remotes/origin/develop
CustomAuth/.git/logs/refs/remotes/origin/master
CustomAuth/.git/objects/00/89591d848a49d4c4890c0391b8a24bf7565839
CustomAuth/.git/objects/00/d1c6519234b83ac6e87693ba1ea66c4d4b92c8
CustomAuth/.git/objects/01/cd4f477ef6dd995847791de7e483073f27811c
CustomAuth/.git/objects/01/cf7b9680e8ce801041cb2c27e32afbcda7e8f1
CustomAuth/.git/objects/02/645794d9dcfb37de6762c8fbc5521810db7944
CustomAuth/.git/objects/02/7e97bc90d75fab57bf0fa87de2d67def4fec5c
CustomAuth/.git/objects/02/bbe1c4c88bf7ae19cc82d36d13bcd900834246
CustomAuth/.git/objects/02/ecffe58108f765afd76c8a838002c69a5be7b6
CustomAuth/.git/objects/02/ff07e4cd643127e8d0d3ae1abb17dc93c3878a
CustomAuth/.git/objects/04/1a4eef69a84d6b8d71ea75905e0e11506307cc
CustomAuth/.git/objects/04/c5c9c0f1e601ec4719698f1e1a299944494ff2
CustomAuth/.git/objects/04/ef2e1f85763caca2d1cca84bdbe1faed076901
CustomAuth/.git/objects/05/3fdd88b4e022bcbf8b8adc5cc6d0a43fcec6dc
CustomAuth/.git/objects/06/44ced095d62dba10d27a58199911eb62364105
django_custom_user_models-0.2.5.dist-info/LICENSE
django_custom_user_models-0.2.5.dist-info/METADATA
django_custom_user_models-0.2.5.dist-info/WHEEL
django_custom_user_models-0.2.5.dist-info/top_level.txt
django_custom_user_models-0.2.5.dist-info/RECORD
