Metadata-Version: 2.1
Name: django-custom-user-models
Version: 0.2.5
Summary: A custom user model for django authentication
Home-page: https://github.com/MHolger77/django-auth
Author: mohammad hosein shamsaei
Author-email: mh.shamsaei.ms@gmail.com
License: UNKNOWN
Platform: UNKNOWN
Classifier: Environment :: Web Environment
Classifier: Programming Language :: Python :: 3
Classifier: License :: OSI Approved :: MIT License
Classifier: Operating System :: OS Independent
Classifier: Framework :: Django
Classifier: Intended Audience :: Developers
Classifier: Topic :: Internet :: WWW/HTTP
Requires-Python: >=3.6
Requires-Dist: jdatetime
Requires-Dist: django-tables2
Requires-Dist: django-phonenumber-field
Requires-Dist: phonenumbers
Requires-Dist: kavenegar
Requires-Dist: django-cryptography
Requires-Dist: pyJWT
